tempyest/__init__.py
tempyest-0.0.0.dist-info/LICENSE.md
tempyest-0.0.0.dist-info/METADATA
tempyest-0.0.0.dist-info/WHEEL
tempyest-0.0.0.dist-info/top_level.txt
tempyest-0.0.0.dist-info/RECORD
