Metadata-Version: 2.1
Name: tempyest
Version: 0.0.0
Summary: Blizzard API Wrapper
Home-page: https://github.com/nevalicjus/tempyest
Author: Nevalicjus
Author-email: nevalicjus@gmail.com
Project-URL: Author, https://n3v.xyz
Project-URL: Bug Tracker, https://github.com/nevalicjus/tempyest/issues
Classifier: Programming Language :: Python :: 3
Classifier: License :: OSI Approved :: MIT License
Classifier: Operating System :: OS Independent
Requires-Python: >=3.6
License-File: LICENSE.md
Requires-Dist: requests
